socws/__init__.py
socws/client.py
socws-0.0.1.dist-info/LICENSE
socws-0.0.1.dist-info/METADATA
socws-0.0.1.dist-info/WHEEL
socws-0.0.1.dist-info/top_level.txt
socws-0.0.1.dist-info/RECORD
