Metadata-Version: 2.1
Name: socws
Version: 0.0.1
Summary: Biblioteca para acesso aos Webservices do Sistema SOC
Home-page: https://github.com/qualitaocupacional/socws
Author: Qualita Seguranca e Saude Ocupacional
Author-email: lab.ti@qualitaocupacional.com.br
License: Apache 2.0
Platform: UNKNOWN
Classifier: Development Status :: 3 - Alpha
Classifier: Intended Audience :: Developers
Classifier: License :: OSI Approved :: Apache Software License
Classifier: Programming Language :: Python :: 2.7
Classifier: Programming Language :: Python :: 3
Classifier: Programming Language :: Python :: 3.7
Classifier: Programming Language :: Python :: 3.8
Requires-Dist: zeep (>=3.4.0)
